osint/__init__.py
osint/__main__.py
osint/osint
osint/qbcached.py
osint/qbdns.py
osint/qbextract.py
osint/qbgetinfo.py
osint/qbhost.py
osint/qbping.py
osint/qbscan.py
osint/qbtraceroute.py
osint/qbwhois.py
osint/data/qbosint.sqlite
osint-0.5.data/scripts/osint
osint-0.5.dist-info/LICENSE
osint-0.5.dist-info/METADATA
osint-0.5.dist-info/WHEEL
osint-0.5.dist-info/top_level.txt
osint-0.5.dist-info/RECORD
