Metadata-Version: 2.1
Name: osint
Version: 0.5
Summary: Collection of Open Source Intelligence (OSINT) tools
Home-page: https://github.com/qeeqbox/osint
Author: QeeqBox
Author-email: gigaqeeq@gmail.com
License: AGPL-3.0
Platform: UNKNOWN
Requires-Python: >=3
Requires-Dist: Pillow
Requires-Dist: beautifulsoup4
Requires-Dist: dnspython
Requires-Dist: langdetect
Requires-Dist: lxml
Requires-Dist: netifaces
Requires-Dist: pyOpenSSL
Requires-Dist: requests
Requires-Dist: scapy
Requires-Dist: tld
